flask_request_params/__init__.py
flask_request_params/params.py
Flask_request_params-0.3.0.dist-info/DESCRIPTION.rst
Flask_request_params-0.3.0.dist-info/METADATA
Flask_request_params-0.3.0.dist-info/metadata.json
Flask_request_params-0.3.0.dist-info/RECORD
Flask_request_params-0.3.0.dist-info/top_level.txt
Flask_request_params-0.3.0.dist-info/WHEEL
tests/__init__.py
tests/base.py
tests/test_request.py
tests/test_strong_parameters.py
