Metadata-Version: 2.0
Name: Flask-request-params
Version: 0.3.0
Summary: Flask-request-params provides Rails-like interface to HTTP Request Parameters for Flask.
Home-page: https://github.com/bluele/flask-request-params
Author: bluele
Author-email: jksmphone@gmail.com
License: MIT
Keywords: flask
Platform: UNKNOWN
Classifier: Development Status :: 4 - Beta
Classifier: Framework :: Flask
Classifier: License :: OSI Approved :: MIT License
Classifier: Programming Language :: Python
Classifier: Programming Language :: Python :: 2
Classifier: Programming Language :: Python :: 2.6
Classifier: Programming Language :: Python :: 2.7
Classifier: Programming Language :: Python :: 3.3
Classifier: Programming Language :: Python :: 3.4
Requires-Dist: flask
